heidelberg_metadata_gui/__init__.py
heidelberg_metadata_gui/cmd_line.py
heidelberg_metadata_gui/config.ini
heidelberg_metadata_gui/config.py
heidelberg_metadata_gui/routes.py
heidelberg_metadata_gui/assets/logo_nwb.png
heidelberg_metadata_gui/assets/stylesheet.css
heidelberg_metadata_gui/examples/__init__.py
heidelberg_metadata_gui/examples/metadata_custom.json
heidelberg_metadata_gui/examples/metadata_ecephys.json
heidelberg_metadata_gui/examples/schema_metadata_custom.json
heidelberg_metadata_gui/examples/schema_metadata_ecephys.json
heidelberg_metadata_gui/examples/schema_metadata_ophys.json
heidelberg_metadata_gui/metadata_forms/__init__.py
heidelberg_metadata_gui/metadata_forms/init_forms.py
heidelberg_metadata_gui/metadata_forms/make_components.py
heidelberg_metadata_gui/metadata_forms/metadata_forms.py
heidelberg_metadata_gui/metadata_forms/navbar.py
tests/__init__.py
tests/conftest.py
tests/test_basics.py
heidelberg_metadata_gui-0.1.2.dist-info/LICENSE
heidelberg_metadata_gui-0.1.2.dist-info/METADATA
heidelberg_metadata_gui-0.1.2.dist-info/WHEEL
heidelberg_metadata_gui-0.1.2.dist-info/entry_points.txt
heidelberg_metadata_gui-0.1.2.dist-info/top_level.txt
heidelberg_metadata_gui-0.1.2.dist-info/RECORD
