Metadata-Version: 2.1
Name: heidelberg-metadata-gui
Version: 0.1.2
Summary: Web graphical user interface for Metadata handling
Home-page: https://github.com/catalystneuro/heidelberg-metadata-gui
Author: Luiz Tauffer, Vinicius Camozzato Vaz and Ben Dichter
Author-email: ben.dichter@gmail.com
License: UNKNOWN
Platform: UNKNOWN
Requires-Dist: attrs (==21.4.0)
Requires-Dist: Brotli (==1.0.9)
Requires-Dist: certifi (==2021.10.8)
Requires-Dist: click (==8.1.2)
Requires-Dist: dash (==2.3.1)
Requires-Dist: dash-bootstrap-components (==0.13.1)
Requires-Dist: dash-cool-components (==0.1.8)
Requires-Dist: dash-core-components (==2.0.0)
Requires-Dist: dash-html-components (==2.0.0)
Requires-Dist: dash-table (==5.0.0)
Requires-Dist: Flask (==2.1.1)
Requires-Dist: Flask-Compress (==1.11)
Requires-Dist: importlib-metadata (==4.11.3)
Requires-Dist: importlib-resources (==5.6.0)
Requires-Dist: itsdangerous (==2.1.2)
Requires-Dist: Jinja2 (==3.1.1)
Requires-Dist: json-schema-to-dash-forms (==0.1.8)
Requires-Dist: jsonschema (==4.4.0)
Requires-Dist: MarkupSafe (==2.1.1)
Requires-Dist: numpy (==1.21.5)
Requires-Dist: plotly (==5.7.0)
Requires-Dist: pyrsistent (==0.18.1)
Requires-Dist: PyYAML (==6.0)
Requires-Dist: six (==1.16.0)
Requires-Dist: tenacity (==8.0.1)
Requires-Dist: typing-extensions (==4.1.1)
Requires-Dist: Werkzeug (==2.1.1)
Requires-Dist: zipp (==3.8.0)
